{
	"name": "LOB_DIM_SQL",
	"properties": {
		"linkedServiceName": {
			"referenceName": "OutputSql",
			"type": "LinkedServiceReference"
		},
		"annotations": [],
		"type": "AzureSqlTable",
		"schema": [
			{
				"name": "SETID",
				"type": "varchar"
			},
			{
				"name": "LOB_ID",
				"type": "varchar"
			},
			{
				"name": "LOB_DESC",
				"type": "varchar"
			},
			{
				"name": "LOB_LEVEL_1_ID",
				"type": "varchar"
			},
			{
				"name": "LOB_LEVEL_2_ID",
				"type": "varchar"
			},
			{
				"name": "LOB_LEVEL_3_ID",
				"type": "varchar"
			},
			{
				"name": "LOB_LEVEL_4_ID",
				"type": "varchar"
			},
			{
				"name": "LOB_LEVEL_1_DESC",
				"type": "varchar"
			},
			{
				"name": "LOB_LEVEL_2_DESC",
				"type": "varchar"
			},
			{
				"name": "LOB_LEVEL_3_DESC",
				"type": "varchar"
			},
			{
				"name": "LOB_LEVEL_4_DESC",
				"type": "varchar"
			},
			{
				"name": "EFFDT",
				"type": "datetime",
				"precision": 23,
				"scale": 3
			},
			{
				"name": "EFF_STATUS",
				"type": "varchar"
			},
			{
				"name": "DTTM_STAMP",
				"type": "datetime",
				"precision": 23,
				"scale": 3
			},
			{
				"name": "OPR_ID",
				"type": "varchar"
			}
		],
		"typeProperties": {
			"schema": "dbo",
			"table": "LOB_DIM"
		}
	}
}